libpythonpro/__init__.py
libpythonpro/github_api.py
gug_libpythonpro-0.2.dist-info/LICENSE
gug_libpythonpro-0.2.dist-info/METADATA
gug_libpythonpro-0.2.dist-info/WHEEL
gug_libpythonpro-0.2.dist-info/top_level.txt
gug_libpythonpro-0.2.dist-info/RECORD
